[{"id":1,"date":"2015-10-12 14:44:14","worker":{"id":1,"name":"worker"},"key":{"id":1,"apartment":{"id":1,"number":5},"customer":{"id":1,"name":"customer"},"name":"my key"}},{"id":2,"date":"2015-14-12 14:44:14","worker":{"id":2,"name":"worker 1"},"key":{"id":1,"apartment":{"id":1,"number":5},"customer":{"id":1,"name":"customer 1"},"name":"my key"}},{"id":3,"date":"2015-14-12 14:44:14","worker":{"id":1,"name":"worker"},"key":{"id":1,"apartment":{"id":1,"number":5},"customer":{"id":2,"name":"Mary"},"name":"my key"}}]
